fast_logomaker/__init__.py
fast_logomaker/colors.py
fast_logomaker/core.py
fast_logomaker/error_handling.py
fast_logomaker-0.1.0.dist-info/licenses/LICENSE
fast_logomaker-0.1.0.dist-info/METADATA
fast_logomaker-0.1.0.dist-info/WHEEL
fast_logomaker-0.1.0.dist-info/top_level.txt
fast_logomaker-0.1.0.dist-info/RECORD
