Metadata-Version: 2.4
Name: fast-logomaker
Version: 0.1.0
Summary: An optimized batch logo generation library for sequence logos
Author: Evan Seitz
License: MIT
Project-URL: Homepage, https://github.com/evanseitz/fast-logomaker
Project-URL: Repository, https://github.com/evanseitz/fast-logomaker
Keywords: logomaker,sequence logo,bioinformatics,batch processing,visualization
Classifier: Development Status :: 4 - Beta
Classifier: Intended Audience :: Science/Research
Classifier: License :: OSI Approved :: MIT License
Classifier: Operating System :: OS Independent
Classifier: Programming Language :: Python :: 3
Classifier: Programming Language :: Python :: 3.8
Classifier: Programming Language :: Python :: 3.9
Classifier: Programming Language :: Python :: 3.10
Classifier: Programming Language :: Python :: 3.11
Classifier: Programming Language :: Python :: 3.12
Classifier: Topic :: Scientific/Engineering :: Bio-Informatics
Classifier: Topic :: Scientific/Engineering :: Visualization
Requires-Python: >=3.8
License-File: LICENSE
Requires-Dist: numpy
Requires-Dist: matplotlib
Requires-Dist: pandas
Requires-Dist: tqdm
Dynamic: license-file
